Metadata-Version: 2.1
Name: bmicalproj
Version: 0.0.1
Summary: A very basic BMI Calculator
Home-page: UNKNOWN
Author: Sanal Sudhakaran
Author-email: sanalsudhakaran@outlook.com
License: MIT
Keywords: bmi
Platform: UNKNOWN
Classifier: Development Status :: 5 - Production/Stable
Classifier: Intended Audience :: Education
Classifier: Operating System :: Microsoft :: Windows :: Windows 10
Classifier: License :: OSI Approved :: MIT License
Classifier: Programming Language :: Python :: 3
License-File: LICENCE.txt
